luxai/magpie/__init__.py
luxai/magpie/assets/magpie.png
luxai/magpie/discovery/__init__.py
luxai/magpie/discovery/mcast_discovery.py
luxai/magpie/discovery/zconf_discovery.py
luxai/magpie/frames/__init__.py
luxai/magpie/frames/audio.py
luxai/magpie/frames/frame.py
luxai/magpie/frames/image.py
luxai/magpie/frames/primitive.py
luxai/magpie/nodes/__init__.py
luxai/magpie/nodes/base_node.py
luxai/magpie/nodes/process_node.py
luxai/magpie/nodes/server_node.py
luxai/magpie/nodes/sink_node.py
luxai/magpie/nodes/source_node.py
luxai/magpie/serializer/__init__.py
luxai/magpie/serializer/base_serializer.py
luxai/magpie/serializer/msgpack_serializer.py
luxai/magpie/tools/__init__.py
luxai/magpie/tools/zmq_audio_player.py
luxai/magpie/tools/zmq_video_capture.py
luxai/magpie/tools/zmq_video_viewer.py
luxai/magpie/transport/__init__.py
luxai/magpie/transport/rpc_requester.py
luxai/magpie/transport/rpc_responder.py
luxai/magpie/transport/stream_reader.py
luxai/magpie/transport/stream_writer.py
luxai/magpie/transport/local/__init__.py
luxai/magpie/transport/local/memory_pushpull.py
luxai/magpie/transport/zmq/__init__.py
luxai/magpie/transport/zmq/zmq_publisher.py
luxai/magpie/transport/zmq/zmq_rpc_requester.py
luxai/magpie/transport/zmq/zmq_rpc_responder.py
luxai/magpie/transport/zmq/zmq_subscriber.py
luxai/magpie/transport/zmq/zmq_utils.py
luxai/magpie/utils/__init__.py
luxai/magpie/utils/common.py
luxai/magpie/utils/logger.py
luxai_magpie-0.6.1.dist-info/licenses/LICENSE
luxai_magpie-0.6.1.dist-info/METADATA
luxai_magpie-0.6.1.dist-info/WHEEL
luxai_magpie-0.6.1.dist-info/entry_points.txt
luxai_magpie-0.6.1.dist-info/top_level.txt
luxai_magpie-0.6.1.dist-info/RECORD
