Metadata-Version: 2.4
Name: luxai-magpie
Version: 0.6.1
Summary: MAGPIE is a lightweight, modular messaging engine providing high-performance pub/sub and RPC over pluggable transports.
Author: LuxAI S.A.
License:                     GNU GENERAL PUBLIC LICENSE
Project-URL: Homepage, https://github.com/luxai-qtrobot/magpie
Project-URL: Source, https://github.com/luxai-qtrobot/magpie
Project-URL: Bug Tracker, https://github.com/luxai-qtrobot/magpie/issues
Keywords: messaging,rpc,pubsub,zeromq,distributed-systems,robotics,middleware
Classifier: Development Status :: 4 - Beta
Classifier: License :: OSI Approved :: GNU General Public License v3 (GPLv3)
Classifier: Programming Language :: Python :: 3
Classifier: Programming Language :: Python :: 3.7
Classifier: Operating System :: OS Independent
Requires-Python: >=3.7.3
License-File: LICENSE
Requires-Dist: typing_extensions
Requires-Dist: python-ulid
Requires-Dist: msgpack
Requires-Dist: pyzmq
Provides-Extra: video
Requires-Dist: numpy; extra == "video"
Requires-Dist: simplejpeg; extra == "video"
Requires-Dist: opencv-python; extra == "video"
Provides-Extra: audio
Requires-Dist: numpy; extra == "audio"
Requires-Dist: soundfile; extra == "audio"
Provides-Extra: discovery
Requires-Dist: zeroconf; extra == "discovery"
Provides-Extra: dev
Requires-Dist: numpy; extra == "dev"
Requires-Dist: opencv-python; extra == "dev"
Requires-Dist: simplejpeg; extra == "dev"
Requires-Dist: soundfile; extra == "dev"
Requires-Dist: pytest; extra == "dev"
Requires-Dist: coverage; extra == "dev"
Provides-Extra: full
Requires-Dist: numpy; extra == "full"
Requires-Dist: opencv-python; extra == "full"
Requires-Dist: simplejpeg; extra == "full"
Requires-Dist: soundfile; extra == "full"
Requires-Dist: zeroconf; extra == "full"
Provides-Extra: cli
Requires-Dist: sounddevice; extra == "cli"
Requires-Dist: numpy; extra == "cli"
Requires-Dist: opencv-python; extra == "cli"
Requires-Dist: simplejpeg; extra == "cli"
Requires-Dist: soundfile; extra == "cli"
Dynamic: license-file
